unicmobile_common/__init__.py
unicmobile_common/aaa_app_client.py
unicmobile_common/dependency_container.py
unicmobile_common/middlewares.py
unicmobile_common-1.0.dist-info/METADATA
unicmobile_common-1.0.dist-info/WHEEL
unicmobile_common-1.0.dist-info/top_level.txt
unicmobile_common-1.0.dist-info/RECORD
